google_api_python_client_helpers-1.2.4.dist-info/METADATA
google_api_python_client_helpers-1.2.4.dist-info/RECORD
google_api_python_client_helpers-1.2.4.dist-info/WHEEL
google_api_python_client_helpers-1.2.4.dist-info/top_level.txt
googleapiclienthelpers/__init__.py
googleapiclienthelpers/discovery.py
googleapiclienthelpers/exceptions.py
googleapiclienthelpers/iam.py
googleapiclienthelpers/waiter.py
