Metadata-Version: 1.1
Name: google-api-python-client-helpers
Version: 1.2.4
Summary: Helpers for Google API Client Library for Python
Home-page: http://github.com/cleardataeng/google-api-python-client-helpers/
Author: Ross  Vandegrift
Author-email: UNKNOWN
License: Apache 2.0
Keywords: google api client
Platform: UNKNOWN
Classifier: Programming Language :: Python :: 2
Classifier: Programming Language :: Python :: 2.7
Classifier: Programming Language :: Python :: 3
Classifier: Programming Language :: Python :: 3.3
Classifier: Programming Language :: Python :: 3.4
Classifier: Programming Language :: Python :: 3.5
Classifier: Programming Language :: Python :: 3.6
Classifier: Programming Language :: Python :: 3.7
Classifier: Development Status :: 5 - Production/Stable
Classifier: Intended Audience :: Developers
Classifier: License :: OSI Approved :: Apache Software License
Classifier: Operating System :: OS Independent
Classifier: Topic :: Internet :: WWW/HTTP
